zone_common/events/base_listener.py
zone_common/events/base_publisher.py
zone_common/events/order_status.py
zone_common/events/subjects.py
zone_common/exceptions/__init__.py
zone_common/exceptions/bad_request_exception.py
zone_common/exceptions/custom_exception.py
zone_common/exceptions/database_exception.py
zone_common/exceptions/not_found_exception.py
zone_common/exceptions/request_validation_exception.py
zone_common/exceptions/unauthorized_exception.py
zone_common/middlewares/current_user.py
zone_common/middlewares/require_auth.py
zone_common-0.0.17.dist-info/METADATA
zone_common-0.0.17.dist-info/WHEEL
zone_common-0.0.17.dist-info/top_level.txt
zone_common-0.0.17.dist-info/RECORD
