Metadata-Version: 2.1
Name: zone-common
Version: 0.0.17
Summary: Common utility package for zone c2c
Home-page: https://github.com/Shreyaschorge/zone_common
Author: Shreyas Chorge
Author-email: shreyaschorge81@gmail.com
Requires-Dist: werkzeug
Requires-Dist: nats-py
Requires-Dist: asyncio
Requires-Dist: python-decouple
Requires-Dist: pyjwt
